Oasys/gRPC/__init__.py
Oasys/gRPC/classes.py
Oasys/gRPC/connection.py
Oasys/gRPC/oasys_pb2.py
Oasys/gRPC/oasys_pb2_grpc.py
oasys_grpc-22.0.0.dist-info/licenses/LICENSE
oasys_grpc-22.0.0.dist-info/METADATA
oasys_grpc-22.0.0.dist-info/WHEEL
oasys_grpc-22.0.0.dist-info/top_level.txt
oasys_grpc-22.0.0.dist-info/RECORD
