Metadata-Version: 2.4
Name: Oasys.gRPC
Version: 22.0.0
Summary: gRPC functions for Oasys D3PLOT, PRIMER, REPORTER and T/HIS
Author: Miles Thornton
Maintainer-email: dyna.support@arup.com
Project-URL: Homepage, https://www.oasys-software.com/dyna/
Keywords: Oasys,gRPC
Requires-Python: >=3.8
License-File: LICENSE
Requires-Dist: grpcio>=1.54.0
Requires-Dist: protobuf
Dynamic: license-file
